LICENSE.txt
MANIFEST.in
README.md
README.rst
mini-spider
mini-spider.json
setup.py
mini_spider.egg-info/PKG-INFO
mini_spider.egg-info/SOURCES.txt
mini_spider.egg-info/dependency_links.txt
mini_spider.egg-info/entry_points.txt
mini_spider.egg-info/top_level.txt
minispider/__init__.py
minispider/__main__.py
minispider/downloader.py
minispider/extractor.py
minispider/scheduler.py
minispider/sql.py
test/test.py