Metadata-Version: 1.0
Name: mini-spider
Version: 0.0.4.2
Summary: Simple way to create your spider.
Home-page: https://github.com/ZYunH/Mini-Spider
Author: ZhangYunHao
Author-email: workvl@163.com
License: MIT Licence
Keywords: p,y,t,h,o,n, ,s,p,i,d,e,r, ,t,o,o,l, ,p,a,c,k,a,g,e
Platform: any
